{
  "name"  : "Aleidy Gomez Estrada",
  "grades": "Ingeniera de Software",
  "mision": "Estudiante de la Universidad veracruzana, Ingeniera en proceso",
  "email" : "alegomezstrada@gmail.com",
  "cel"   : "+52 287 145 34 32",
  "foto": "https://scontent-dfw5-2.xx.fbcdn.net/v/t39.30808-6/290058913_558147865987449_9103724112511872650_n.jpg?_nc_cat=109&ccb=1-7&_nc_sid=1b51e3&_nc_ohc=tAUDaqsiPkwAX-TvdDJ&_nc_ht=scontent-dfw5-2.xx&oh=00_AfCraX3cpJxL-PaHcg7-qWxRmRLaXkQ0QUXH5O5snHlwdw&oe=650A51B0",
  "redsocial": "@Alegxmx",
  "ubication": "Orizaba,Veracruz"
}